README.rst
setup.py
silentiary.py
silentiary.egg-info/PKG-INFO
silentiary.egg-info/SOURCES.txt
silentiary.egg-info/dependency_links.txt
silentiary.egg-info/requires.txt
silentiary.egg-info/top_level.txt