Metadata-Version: 1.1
Name: silentiary
Version: 0.1.0
Summary: Password manager
Home-page: https://github.com/arthurdick/silentiary
Author: Arthur Dick
Author-email: arthur@arthurdick.com
License: GPLv3
Keywords: password
Platform: UNKNOWN
Classifier: Development Status :: 2 - Pre-Alpha
Classifier: Environment :: Console
Classifier: Intended Audience :: End Users/Desktop
Classifier: License :: OSI Approved :: GNU General Public License v3 (GPLv3)
Classifier: Natural Language :: English
Classifier: Operating System :: POSIX :: Linux
Classifier: Programming Language :: Python :: 3 :: Only
Classifier: Topic :: Security
